LICENSE
MANIFEST.in
README.md
pyproject.toml
setup.py
dev_tools/build.py
dev_tools/mock_gumroad.py
dev_tools/setup_model.py
dev_tools/stress_test_upif.py
dev_tools/verify_licensing.py
dev_tools/verify_neural.py
dev_tools/verify_upif.py
test_env/Lib/site-packages/typing_extensions.py
test_env/Lib/site-packages/_distutils_hack/__init__.py
test_env/Lib/site-packages/_distutils_hack/override.py
test_env/Lib/site-packages/annotated_types/__init__.py
test_env/Lib/site-packages/annotated_types/test_cases.py
test_env/Lib/site-packages/certifi/__init__.py
test_env/Lib/site-packages/certifi/__main__.py
test_env/Lib/site-packages/certifi/core.py
test_env/Lib/site-packages/cffi/__init__.py
test_env/Lib/site-packages/cffi/_imp_emulation.py
test_env/Lib/site-packages/cffi/_shimmed_dist_utils.py
test_env/Lib/site-packages/cffi/api.py
test_env/Lib/site-packages/cffi/backend_ctypes.py
test_env/Lib/site-packages/cffi/cffi_opcode.py
test_env/Lib/site-packages/cffi/commontypes.py
test_env/Lib/site-packages/cffi/cparser.py
test_env/Lib/site-packages/cffi/error.py
test_env/Lib/site-packages/cffi/ffiplatform.py
test_env/Lib/site-packages/cffi/lock.py
test_env/Lib/site-packages/cffi/model.py
test_env/Lib/site-packages/cffi/pkgconfig.py
test_env/Lib/site-packages/cffi/recompiler.py
test_env/Lib/site-packages/cffi/setuptools_ext.py
test_env/Lib/site-packages/cffi/vengine_cpy.py
test_env/Lib/site-packages/cffi/vengine_gen.py
test_env/Lib/site-packages/cffi/verifier.py
test_env/Lib/site-packages/charset_normalizer/__init__.py
test_env/Lib/site-packages/charset_normalizer/__main__.py
test_env/Lib/site-packages/charset_normalizer/api.py
test_env/Lib/site-packages/charset_normalizer/cd.py
test_env/Lib/site-packages/charset_normalizer/constant.py
test_env/Lib/site-packages/charset_normalizer/legacy.py
test_env/Lib/site-packages/charset_normalizer/md.py
test_env/Lib/site-packages/charset_normalizer/models.py
test_env/Lib/site-packages/charset_normalizer/utils.py
upif.egg-info/PKG-INFO
upif.egg-info/SOURCES.txt
upif.egg-info/dependency_links.txt
upif.egg-info/entry_points.txt
upif.egg-info/not-zip-safe
upif.egg-info/requires.txt
upif.egg-info/top_level.txt
