Metadata-Version: 2.1
Name: upif
Version: 0.1.4
Summary: Universal Prompt Injection Firewall - A local-first AI security layer.
Author-email: Yash Dhone <yash.dhone01@gmail.com>
Classifier: Programming Language :: Python :: 3
Classifier: License :: OSI Approved :: MIT License
Classifier: Operating System :: OS Independent
Requires-Python: >=3.10
Provides-Extra: pro
Provides-Extra: dev
License-File: LICENSE
